sentry_dingtalk_notify/__init__.py
sentry_dingtalk_notify/plugin.py
sentry_dingtalks_notify-1.0.0.dist-info/LICENSE
sentry_dingtalks_notify-1.0.0.dist-info/METADATA
sentry_dingtalks_notify-1.0.0.dist-info/WHEEL
sentry_dingtalks_notify-1.0.0.dist-info/entry_points.txt
sentry_dingtalks_notify-1.0.0.dist-info/top_level.txt
sentry_dingtalks_notify-1.0.0.dist-info/RECORD
