Metadata-Version: 2.1
Name: sentry-dingtalks-notify
Version: 1.0.0
Summary: A sentry extension integrates DingTalk robot webhook
Home-page: https://github.com/damengzhang/sentry-dingtalks-notify
Author: damengzhang
Author-email: damengzhang@163.com
License: MIT
Keywords: sentry dingtalk
Classifier: License :: OSI Approved :: MIT License
Classifier: Programming Language :: Python
Classifier: Programming Language :: Python :: 3
Classifier: Programming Language :: Python :: 3.6
Classifier: Programming Language :: Python :: 3.7
Classifier: Programming Language :: Python :: Implementation :: CPython
Requires-Python: >=3.6.13
License-File: LICENSE
Requires-Dist: sentry>=21.5.1
